selenoprofiles4/MMlib3.py
selenoprofiles4/__init__.py
selenoprofiles4/_version.py
selenoprofiles4/blaster_parser.awk
selenoprofiles4/load_config.py
selenoprofiles4/selenoprofiles4.py
selenoprofiles4/selenoprofiles_assess.py
selenoprofiles4/selenoprofiles_build_profile.py
selenoprofiles4/selenoprofiles_database.py
selenoprofiles4/selenoprofiles_join_alignments.py
selenoprofiles4/selenoprofiles_lineage.py
selenoprofiles4/selenoprofiles_orthology.py
selenoprofiles4/selenoprofiles_test.py
selenoprofiles4/selenoprofiles_tree_drawer.py
selenoprofiles4/exoneratecfg/BLOSUM62sel
selenoprofiles4/tests/test_sequences.fa
selenoprofiles4/wisecfg/BLOSUM62sel.bla
selenoprofiles4/wisecfg/codon.table.gc1.sec
selenoprofiles4/wisecfg/codon.table.gc1.std
selenoprofiles4/wisecfg/codon.table.gc10.sec
selenoprofiles4/wisecfg/codon.table.gc10.std
selenoprofiles4/wisecfg/codon.table.gc11.sec
selenoprofiles4/wisecfg/codon.table.gc11.std
selenoprofiles4/wisecfg/codon.table.gc12.sec
selenoprofiles4/wisecfg/codon.table.gc12.std
selenoprofiles4/wisecfg/codon.table.gc13.sec
selenoprofiles4/wisecfg/codon.table.gc13.std
selenoprofiles4/wisecfg/codon.table.gc14.sec
selenoprofiles4/wisecfg/codon.table.gc14.std
selenoprofiles4/wisecfg/codon.table.gc16.sec
selenoprofiles4/wisecfg/codon.table.gc16.std
selenoprofiles4/wisecfg/codon.table.gc2.sec
selenoprofiles4/wisecfg/codon.table.gc2.std
selenoprofiles4/wisecfg/codon.table.gc21.sec
selenoprofiles4/wisecfg/codon.table.gc21.std
selenoprofiles4/wisecfg/codon.table.gc22.sec
selenoprofiles4/wisecfg/codon.table.gc22.std
selenoprofiles4/wisecfg/codon.table.gc23.sec
selenoprofiles4/wisecfg/codon.table.gc23.std
selenoprofiles4/wisecfg/codon.table.gc24.sec
selenoprofiles4/wisecfg/codon.table.gc24.std
selenoprofiles4/wisecfg/codon.table.gc25.sec
selenoprofiles4/wisecfg/codon.table.gc25.std
selenoprofiles4/wisecfg/codon.table.gc26.sec
selenoprofiles4/wisecfg/codon.table.gc26.std
selenoprofiles4/wisecfg/codon.table.gc27.sec
selenoprofiles4-4.5.7.dist-info/licenses/LICENSE
selenoprofiles4-4.5.7.dist-info/METADATA
selenoprofiles4-4.5.7.dist-info/WHEEL
selenoprofiles4-4.5.7.dist-info/entry_points.txt
selenoprofiles4-4.5.7.dist-info/top_level.txt
selenoprofiles4-4.5.7.dist-info/RECORD
